bak/__init__.py
bak/__main__.py
bak/backup.py
bak/clean.py
bak/config.py
bak/helpers.py
bak/logger.py
bak/main.py
bak/rescue.py
bak/tests/test_logger.py
dim_bak-25.5.2.dist-info/licenses/LICENSE
dim_bak-25.5.2.dist-info/METADATA
dim_bak-25.5.2.dist-info/WHEEL
dim_bak-25.5.2.dist-info/entry_points.txt
dim_bak-25.5.2.dist-info/top_level.txt
dim_bak-25.5.2.dist-info/RECORD
