Metadata-Version: 2.4
Name: dim-bak
Version: 25.5.2
Summary: Uma ferramenta de linha de comando simples e rápida para fazer backups temporários de arquivos e diretórios.
Author: Dimitri Miranda
License: MIT
License-File: LICENSE
Dynamic: license-file
